{
  "minecraft:recipes/misc/charcoal": {
    "criteria": {
      "has_log": "2023-04-03 15:34:50 +0000"
    },
    "done": true
  },
  "minecraft:recipes/building_blocks/spruce_planks": {
    "criteria": {
      "has_logs": "2023-04-03 15:34:50 +0000"
    },
    "done": true
  },
  "minecraft:recipes/building_blocks/spruce_wood": {
    "criteria": {
      "has_log": "2023-04-03 15:34:50 +0000"
    },
    "done": true
  },
  "minecraft:adventure/adventuring_time": {
    "criteria": {
      "minecraft:grove": "2023-04-03 15:34:25 +0000"
    },
    "done": false
  },
  "DataVersion": 3120
}